coc_api/__init__.py
coc_api/cache.py
coc_api/client.py
coc_api/endpoints/__init__.py
coc_api/endpoints/clan.py
coc_api/endpoints/goldpass.py
coc_api/endpoints/players.py
coc_api/exceptions.py
coc_api/models/__init__.py
coc_api/models/achievement.py
coc_api/models/clan.py
coc_api/models/clan_capital.py
coc_api/models/clan_capital_house.py
coc_api/models/district.py
coc_api/models/equipment.py
coc_api/models/goldpass.py
coc_api/models/hero.py
coc_api/models/label.py
coc_api/models/league.py
coc_api/models/location.py
coc_api/models/player.py
coc_api/models/spell.py
coc_api/models/troop.py
coc_api/utils/__init__.py
coc_api/utils/cache_result.py
clash_of_clans_python_api-0.2.5.dist-info/LICENSE
clash_of_clans_python_api-0.2.5.dist-info/METADATA
clash_of_clans_python_api-0.2.5.dist-info/WHEEL
clash_of_clans_python_api-0.2.5.dist-info/RECORD
