Metadata-Version: 2.3
Name: clash-of-clans-python-api
Version: 0.2.5
Summary: A wrapper for the official Clash of Clans API.
License: MIT
Author: TheBiemGamer
Author-email: biemgamer@pm.me
Requires-Python: >=3.11
Classifier: License :: OSI Approved :: MIT License
Classifier: Programming Language :: Python :: 3
Classifier: Programming Language :: Python :: 3.11
Classifier: Programming Language :: Python :: 3.12
Classifier: Programming Language :: Python :: 3.13
Requires-Dist: httpx (>=0.28.1,<0.29.0)
Requires-Dist: python-dotenv (>=1.1.0,<2.0.0)
Project-URL: Source Code, https://github.com/TheBiemGamer/ClashOfClansPythonAPI
